plastron/client/__init__.py
plastron/client/auth.py
plastron_client-4.6.2.dist-info/METADATA
plastron_client-4.6.2.dist-info/WHEEL
plastron_client-4.6.2.dist-info/top_level.txt
plastron_client-4.6.2.dist-info/RECORD
