Metadata-Version: 2.4
Name: plastron-client
Version: 4.6.2
Summary: HTTP client for interacting with Fedora 4 repositories
Author-email: University of Maryland Libraries <lib-ssdr@umd.edu>, Josh Westgard <westgard@umd.edu>, Peter Eichman <peichman@umd.edu>, Mohamed Abdul Rasheed <mohideen@umd.edu>, Ben Wallberg <wallberg@umd.edu>, David Steelman <dsteelma@umd.edu>, Marc Andreu Grillo Aguilar <aguilarm@umd.edu>
Requires-Python: >=3.10
Requires-Dist: rdflib
Requires-Dist: requests
Requires-Dist: requests-jwtauth
Requires-Dist: urlobject
Provides-Extra: test
Requires-Dist: freezegun; extra == "test"
Requires-Dist: http-server-mock; extra == "test"
Requires-Dist: pytest; extra == "test"
Requires-Dist: pytest-cov; extra == "test"
